<annotation>
	<folder>images</folder>
	<filename>073.jpg</filename>
	<path>C:\Users\DEcade\Desktop\datasets\train\images\073.jpg</path>
	<source>
		<database>Unknown</database>
	</source>
	<size>
		<width>3648</width>
		<height>2736</height>
		<depth>3</depth>
	</size>
	<segmented>0</segmented>
	<object>
		<name>green</name>
		<pose>Unspecified</pose>
		<truncated>0</truncated>
		<difficult>0</difficult>
		<bndbox>
			<xmin>268</xmin>
			<ymin>800</ymin>
			<xmax>791</xmax>
			<ymax>1638</ymax>
		</bndbox>
	</object>
	<object>
		<name>red</name>
		<pose>Unspecified</pose>
		<truncated>0</truncated>
		<difficult>0</difficult>
		<bndbox>
			<xmin>1506</xmin>
			<ymin>807</ymin>
			<xmax>1810</xmax>
			<ymax>1698</ymax>
		</bndbox>
	</object>
	<object>
		<name>black</name>
		<pose>Unspecified</pose>
		<truncated>1</truncated>
		<difficult>0</difficult>
		<bndbox>
			<xmin>2550</xmin>
			<ymin>797</ymin>
			<xmax>3648</xmax>
			<ymax>2278</ymax>
		</bndbox>
	</object>
</annotation>
