<annotation>
	<folder>images</folder>
	<filename>085.jpg</filename>
	<path>C:\Users\DEcade\Desktop\datasets\train\images\085.jpg</path>
	<source>
		<database>Unknown</database>
	</source>
	<size>
		<width>3648</width>
		<height>2736</height>
		<depth>3</depth>
	</size>
	<segmented>0</segmented>
	<object>
		<name>green</name>
		<pose>Unspecified</pose>
		<truncated>0</truncated>
		<difficult>0</difficult>
		<bndbox>
			<xmin>1423</xmin>
			<ymin>967</ymin>
			<xmax>2045</xmax>
			<ymax>1868</ymax>
		</bndbox>
	</object>
</annotation>
